arducamdepthcamera-0.1.23.dist-info/METADATA
arducamdepthcamera-0.1.23.dist-info/WHEEL
arducamdepthcamera-0.1.23.dist-info/RECORD
arducamdepthcamera-0.1.23.dist-info/top_level.txt
ArducamDepthCamera/ArducamDepthCamera.pyi
ArducamDepthCamera/ArducamDepthCamera.cpython-311-arm-linux-gnueabihf.so
ArducamDepthCamera/__init__.py
arducamdepthcamera.libs/libsi4c-059d33e1.so
arducamdepthcamera.libs/libarducam_config_parser-20eb9161.so
arducamdepthcamera.libs/libgomp-3dab5749.so.1.0.0
arducamdepthcamera.libs/libarducam_evk_sdk-f2ec0971.so.1.0.8
