Metadata-Version: 2.1
Name: arducamdepthcamera
Version: 0.1.23
Summary: Driver development kit for arducam tof camera
Home-page: UNKNOWN
Author: Arducam <support@arducam.com>
Author-email: UNKNOWN
License: UNKNOWN
Platform: UNKNOWN
Requires-Dist: numpy (<2.0.0)
